jax_pcmci/__init__.py
jax_pcmci/config.py
jax_pcmci/data.py
jax_pcmci/jax_utils.py
jax_pcmci/parallel.py
jax_pcmci/precompile.py
jax_pcmci/results.py
jax_pcmci/algorithms/__init__.py
jax_pcmci/algorithms/pcmci.py
jax_pcmci/algorithms/pcmci_plus.py
jax_pcmci/independence_tests/__init__.py
jax_pcmci/independence_tests/base.py
jax_pcmci/independence_tests/cmi_knn.py
jax_pcmci/independence_tests/gpdc.py
jax_pcmci/independence_tests/parcorr.py
jax_pcmci-1.3.0.dist-info/licenses/LICENSE
jax_pcmci-1.3.0.dist-info/METADATA
jax_pcmci-1.3.0.dist-info/WHEEL
jax_pcmci-1.3.0.dist-info/top_level.txt
jax_pcmci-1.3.0.dist-info/RECORD
