Metadata-Version: 2.4
Name: JAX-PCMCI
Version: 1.3.0
Summary: High-performance causal discovery using PCMCI algorithms with JAX acceleration
Author: JAX-PCMCI Contributors
License: MIT
Project-URL: Homepage, https://github.com/gpgabriel25/JAX-PCMCI
Project-URL: Repository, https://github.com/gpgabriel25/JAX-PCMCI
Keywords: causal-discovery,pcmci,jax,time-series,causality
Classifier: Development Status :: 4 - Beta
Classifier: Intended Audience :: Science/Research
Classifier: License :: OSI Approved :: MIT License
Classifier: Programming Language :: Python :: 3
Classifier: Programming Language :: Python :: 3.9
Classifier: Programming Language :: Python :: 3.10
Classifier: Programming Language :: Python :: 3.11
Classifier: Programming Language :: Python :: 3.12
Classifier: Topic :: Scientific/Engineering :: Artificial Intelligence
Classifier: Topic :: Scientific/Engineering :: Information Analysis
Requires-Python: >=3.9
License-File: LICENSE
Requires-Dist: jax>=0.4.20
Requires-Dist: jaxlib>=0.4.20
Requires-Dist: numpy>=1.24.0
Requires-Dist: scipy>=1.10.0
Requires-Dist: networkx>=3.0
Requires-Dist: matplotlib>=3.7.0
Requires-Dist: tqdm>=4.65.0
Provides-Extra: dev
Requires-Dist: pytest>=7.0.0; extra == "dev"
Requires-Dist: pytest-cov>=4.0.0; extra == "dev"
Requires-Dist: black>=23.0.0; extra == "dev"
Requires-Dist: ruff>=0.1.0; extra == "dev"
Requires-Dist: mypy>=1.0.0; extra == "dev"
Requires-Dist: pre-commit>=3.0.0; extra == "dev"
Provides-Extra: docs
Requires-Dist: sphinx>=6.0.0; extra == "docs"
Requires-Dist: sphinx-rtd-theme>=1.3.0; extra == "docs"
Requires-Dist: sphinx-autodoc-typehints>=1.22.0; extra == "docs"
Requires-Dist: nbsphinx>=0.9.0; extra == "docs"
Requires-Dist: myst-parser>=1.0.0; extra == "docs"
Provides-Extra: gpu
Requires-Dist: jax[cuda12_pip]>=0.4.20; extra == "gpu"
Provides-Extra: tpu
Requires-Dist: jax[tpu]>=0.4.20; extra == "tpu"
Dynamic: license-file
